odoo/addons/ddmrp_packaging_product_replace/README.rst
odoo/addons/ddmrp_packaging_product_replace/__init__.py
odoo/addons/ddmrp_packaging_product_replace/__manifest__.py
odoo/addons/ddmrp_packaging_product_replace/i18n/ddmrp_packaging_product_replace.pot
odoo/addons/ddmrp_packaging_product_replace/i18n/it.po
odoo/addons/ddmrp_packaging_product_replace/readme/CONTRIBUTORS.md
odoo/addons/ddmrp_packaging_product_replace/readme/DESCRIPTION.md
odoo/addons/ddmrp_packaging_product_replace/static/description/icon.png
odoo/addons/ddmrp_packaging_product_replace/static/description/index.html
odoo/addons/ddmrp_packaging_product_replace/tests/__init__.py
odoo/addons/ddmrp_packaging_product_replace/tests/test_product_replace_packaging.py
odoo/addons/ddmrp_packaging_product_replace/wizards/__init__.py
odoo/addons/ddmrp_packaging_product_replace/wizards/ddmrp_product_replace.py
odoo_addon_ddmrp_packaging_product_replace-18.0.1.0.0.4.dist-info/METADATA
odoo_addon_ddmrp_packaging_product_replace-18.0.1.0.0.4.dist-info/WHEEL
odoo_addon_ddmrp_packaging_product_replace-18.0.1.0.0.4.dist-info/top_level.txt
odoo_addon_ddmrp_packaging_product_replace-18.0.1.0.0.4.dist-info/RECORD
