Metadata-Version: 2.1
Name: odoo-addon-ddmrp_packaging_product_replace
Version: 18.0.1.0.0.4
Requires-Python: >=3.10
Requires-Dist: odoo-addon-ddmrp_packaging==18.0.*
Requires-Dist: odoo-addon-ddmrp_product_replace==18.0.*
Requires-Dist: odoo==18.0.*
Summary: Glue module for DDMRP packaging and product replace
Home-page: https://github.com/OCA/ddmrp
License: LGPL-3
Author: Camptocamp SA, Odoo Community Association (OCA)
Author-email: support@odoo-community.org
Classifier: Programming Language :: Python
Classifier: Framework :: Odoo
Classifier: Framework :: Odoo :: 18.0
Classifier: License :: OSI Approved :: GNU Lesser General Public License v3 (LGPLv3)
